[{"brand":"www.staples.com","url":"https://www.staples.com/4xem-cable-ties-10-x-0-16-white-250-pack-4x10ziptie250w/product_IM18HY748","price":"16.49"},{"brand":"www.provantage.com","url":"https://www.provantage.com/4xem-4x10ziptie250w~74XEM159.htm","price":"12.84"},{"brand":"www.shi.com","url":"https://www.shi.com/Product/42069413/4XEM-Cable-tie-25.4-cm","price":"13.00"},{"brand":"www.insight.com","url":"https://www.insight.com/en_US/shop/product/4X10ZIPTIE250W/4XEM%20CORP./4X10ZIPTIE250W/4XEM-cable-tie/","price":"14.99"}]